Metadata-Version: 2.1
Name: django-tracer
Version: 0.9.3
Summary: django-tracer gives you an easy way to generate and use a UUID per request
Home-page: https://github.com/revsys/django-tracer/
Author: Frank Wiles
Author-email: frank@revsys.com
License: UNKNOWN
Platform: UNKNOWN
Classifier: Development Status :: 4 - Beta
Classifier: Environment :: Web Environment
Classifier: Intended Audience :: Developers
Classifier: License :: OSI Approved :: BSD License
Classifier: Operating System :: OS Independent
Classifier: Programming Language :: Python :: 3
Classifier: Framework :: Django
